dlpoly/__init__.py
dlpoly/__main__.py
dlpoly/calculator.py
dlpoly/cli.py
dlpoly/config.py
dlpoly/control.py
dlpoly/correlations.py
dlpoly/currents.py
dlpoly/dlpoly.py
dlpoly/field.py
dlpoly/msd.py
dlpoly/new_control.py
dlpoly/output.py
dlpoly/rdf.py
dlpoly/species.py
dlpoly/statis.py
dlpoly/utility.py
dlpoly_py-0.4.1.dist-info/LICENSE
dlpoly_py-0.4.1.dist-info/METADATA
dlpoly_py-0.4.1.dist-info/WHEEL
dlpoly_py-0.4.1.dist-info/top_level.txt
dlpoly_py-0.4.1.dist-info/RECORD
