Metadata-Version: 2.1
Name: dlpoly-py
Version: 0.4.1
Summary: dlpoly4 python module for file manipulation
Home-page: https://gitlab.com/drFaustroll/dlpoly-py
Author: Alin M Elena, Jacob Wilkins
Author-email: alinm.elena@gmail.com, jacob.wilkins@oerc.ox.ac.uk
License: BSD-3
Classifier: Development Status :: 4 - Beta
Classifier: Programming Language :: Python :: 3
Classifier: License :: OSI Approved :: BSD License
Classifier: Operating System :: OS Independent
Classifier: Topic :: Scientific/Engineering :: Physics
Classifier: Topic :: Scientific/Engineering :: Chemistry
License-File: LICENSE
Requires-Dist: numpy >=1.5.0
Requires-Dist: matplotlib >=2.0.0
Requires-Dist: flake8
Requires-Dist: ruamel.yaml
Requires-Dist: coverage
Requires-Dist: pytest
Requires-Dist: pytest-cov
Requires-Dist: tox
Requires-Dist: sphinx
